slack_logger.py
slack_logger-0.3.1.dist-info/DESCRIPTION.rst
slack_logger-0.3.1.dist-info/METADATA
slack_logger-0.3.1.dist-info/RECORD
slack_logger-0.3.1.dist-info/WHEEL
slack_logger-0.3.1.dist-info/metadata.json
slack_logger-0.3.1.dist-info/top_level.txt
