Metadata-Version: 2.0
Name: slack-logger
Version: 0.3.1
Summary: A Python logging handler for Slack integration
Home-page: https://github.com/junhwi/python-slack-logger
Author: Junhwi Kim
Author-email: junhwi.kim23@gmail.com
License: MIT
Keywords: slack logging
Platform: UNKNOWN
Classifier: Development Status :: 5 - Production/Stable
Classifier: Intended Audience :: Developers
Classifier: Topic :: Communications :: Chat
Classifier: Topic :: System :: Logging
Classifier: License :: OSI Approved :: MIT License
Classifier: Programming Language :: Python :: 3
Classifier: Programming Language :: Python :: 3.3
Classifier: Programming Language :: Python :: 3.4
Classifier: Programming Language :: Python :: 3.5
